Metadata-Version: 1.1
Name: ants
Version: 0.0.7
Summary: A human spider framework base on django
Home-page: https://github.com/mymusise/ants
Author: mymusise
Author-email: mymusise1@gmail.com
License: MIT
Keywords: spider django human
Platform: UNKNOWN
Classifier: Development Status :: 5 - Production/Stable
Classifier: Environment :: Web Environment
Classifier: Intended Audience :: Developers
Classifier: License :: OSI Approved :: MIT License
Classifier: Framework :: Django
Classifier: Programming Language :: Python
Classifier: Programming Language :: Python :: 3
Classifier: Programming Language :: Python :: 2.7
Classifier: Topic :: Software Development
